pyroll/ring_model.py
pyroll_ring_model-3.0.0.dist-info/METADATA
pyroll_ring_model-3.0.0.dist-info/WHEEL
pyroll_ring_model-3.0.0.dist-info/licenses/LICENSE
pyroll_ring_model-3.0.0.dist-info/RECORD
